django_huey_logger-1.0.0.dist-info/RECORD
django_huey_logger-1.0.0.dist-info/metadata.json
django_huey_logger-1.0.0.dist-info/WHEEL
django_huey_logger-1.0.0.dist-info/DESCRIPTION.rst
django_huey_logger-1.0.0.dist-info/top_level.txt
django_huey_logger-1.0.0.dist-info/METADATA
tests/__init__.py
tests/test_main.py
huey_logger/models.py
huey_logger/__init__.py
huey_logger/apps.py
huey_logger/admin.py
huey_logger/decorators.py
huey_logger/migrations/__init__.py
huey_logger/migrations/0001_initial.py
