Metadata-Version: 2.0
Name: django-huey-logger
Version: 1.0.0
Summary: A simple Django app to let you know if huey tasks are working without errors.
Home-page: https://github.com/lotrekagency/django-huey-logger
Author: Gabriele Baldi
Author-email: gabriele.baldi.01@gmail.com
License: MIT
Platform: UNKNOWN
Classifier: Environment :: Web Environment
Classifier: Framework :: Django
Classifier: Intended Audience :: Developers
Classifier: License :: OSI Approved :: MIT License
Classifier: Operating System :: OS Independent
Classifier: Programming Language :: Python :: 3.5
Classifier: Programming Language :: Python :: 3.6
Classifier: Topic :: Internet :: WWW/HTTP
Classifier: Topic :: Internet :: WWW/HTTP :: Dynamic Content
